{
  "meta": {
    "description": "Westwood / UCLA-area rental listings compiled from public Zillow listing pages (May 2026 snapshot). Not live API data — refresh periodically for demos.",
    "source": "zillow",
    "region": "Westwood, Los Angeles, CA (90024, 90025)",
    "compiled_at": "2026-06-05",
    "listing_count": 40,
    "attribution": "Listing data sourced from publicly visible Zillow pages. Zillow® is a registered trademark of Zillow Group.",
    "geocoded_at": "2026-06-05T07:23:19.008Z",
    "geocode_source": "OpenStreetMap Nominatim"
  },
  "listings": [
    {
      "external_id": "5k7f24-230",
      "source": "zillow",
      "name": "Lumiere at Malcolm - Unit 230",
      "address_line": "1644 Malcolm Ave #230",
      "city": "Los Angeles",
      "state": "CA",
      "zip": "90024",
      "neighborhood": "Westwood",
      "lat": 34.0532881,
      "lng": -118.4371495,
      "monthly_rent": 13750,
      "bedrooms": 3,
      "bathrooms": 3.5,
      "sqft": 2833,
      "property_type": "apartment",
      "photos": [
        "https://photos.zillowstatic.com/fp/e6f7e0860027519650e35f92b604dc5e-p_e.jpg",
        "https://photos.zillowstatic.com/fp/153fb7935fca1b3f2ebb79874ca02bc2-p_e.jpg"
      ],
      "listing_url": "https://www.zillow.com/apartments/los-angeles-ca/lumiere-at-malcolm-luxury-homes/5k7f24/"
    },
    {
      "external_id": "5XryM8-1bd",
      "source": "zillow",
      "name": "Strathmore Veteran - 1 Bed",
      "address_line": "11090 Strathmore Dr",
      "city": "Los Angeles",
      "state": "CA",
      "zip": "90024",
      "neighborhood": "Westwood",
      "lat": 34.064013,
      "lng": -118.452805,
      "monthly_rent": 2694,
      "bedrooms": 1,
      "bathrooms": 1,
      "sqft": null,
      "property_type": "apartment",
      "photos": [
        "https://photos.zillowstatic.com/fp/6264a7cfaaba96736915a46d7853da8f-p_e.jpg"
      ],
      "listing_url": "https://www.zillow.com/apartments/los-angeles-ca/strathmore-veteran/5XryM8/"
    },
    {
      "external_id": "5XryM8-2bd",
      "source": "zillow",
      "name": "Strathmore Veteran - 2 Bed",
      "address_line": "11090 Strathmore Dr",
      "city": "Los Angeles",
      "state": "CA",
      "zip": "90024",
      "neighborhood": "Westwood",
      "lat": 34.064013,
      "lng": -118.452805,
      "monthly_rent": 4186,
      "bedrooms": 2,
      "bathrooms": 2,
      "sqft": null,
      "property_type": "apartment",
      "photos": [
        "https://photos.zillowstatic.com/fp/006e6b1e3d9a8a2a4a4dd09bbc36ecbb-p_e.jpg"
      ],
      "listing_url": "https://www.zillow.com/apartments/los-angeles-ca/strathmore-veteran/5XryM8/"
    },
    {
      "external_id": "5XkJC3-studio",
      "source": "zillow",
      "name": "Westwood Village Apartments - Studio",
      "address_line": "1033 Hilgard Ave",
      "city": "Los Angeles",
      "state": "CA",
      "zip": "90024",
      "neighborhood": "Westwood",
      "lat": 34.0606787,
      "lng": -118.4422739,
      "monthly_rent": 3277,
      "bedrooms": 0,
      "bathrooms": 1,
      "sqft": null,
      "property_type": "apartment",
      "photos": [
        "https://photos.zillowstatic.com/fp/bc5ee15be6aed9d2ad53c8e75d731f68-p_e.jpg"
      ],
      "listing_url": "https://www.zillow.com/apartments/los-angeles-ca/westwood-village-apartments/5XkJC3/"
    },
    {
      "external_id": "5XkJC3-1bd",
      "source": "zillow",
      "name": "Westwood Village Apartments - 1 Bed",
      "address_line": "1033 Hilgard Ave #406",
      "city": "Los Angeles",
      "state": "CA",
      "zip": "90024",
      "neighborhood": "Westwood",
      "lat": 34.0606787,
      "lng": -118.4422739,
      "monthly_rent": 3415,
      "bedrooms": 1,
      "bathrooms": 1,
      "sqft": 680,
      "property_type": "apartment",
      "photos": [
        "https://photos.zillowstatic.com/fp/cbf9592240656b16a2909d5c926e0221-p_e.jpg"
      ],
      "listing_url": "https://www.zillow.com/apartments/los-angeles-ca/westwood-village-apartments/5XkJC3/"
    },
    {
      "external_id": "5XpDsf-1bd",
      "source": "zillow",
      "name": "Axiom Westwood - 1 Bed",
      "address_line": "415 Gayley Ave #K135",
      "city": "Los Angeles",
      "state": "CA",
      "zip": "90024",
      "neighborhood": "Westwood",
      "lat": 34.0702595,
      "lng": -118.454441,
      "monthly_rent": 2583,
      "bedrooms": 1,
      "bathrooms": 1,
      "sqft": null,
      "property_type": "apartment",
      "photos": [
        "https://photos.zillowstatic.com/fp/660b9cd2930675dafcc7309547704c92-p_e.jpg"
      ],
      "listing_url": "https://www.zillow.com/apartments/los-angeles-ca/axiom-westwood/5XpDsf/"
    },
    {
      "external_id": "5XpDsf-2bd",
      "source": "zillow",
      "name": "Axiom Westwood - 2 Bed",
      "address_line": "415 Gayley Ave",
      "city": "Los Angeles",
      "state": "CA",
      "zip": "90024",
      "neighborhood": "Westwood",
      "lat": 34.0702595,
      "lng": -118.454441,
      "monthly_rent": 3798,
      "bedrooms": 2,
      "bathrooms": 2,
      "sqft": null,
      "property_type": "apartment",
      "photos": [
        "https://photos.zillowstatic.com/fp/7ae99a2d9668c72aa536811ba786f431-p_e.jpg"
      ],
      "listing_url": "https://www.zillow.com/apartments/los-angeles-ca/axiom-westwood/5XpDsf/"
    },
    {
      "external_id": "5XjxTv-studio",
      "source": "zillow",
      "name": "BMV Properties - Studio",
      "address_line": "690 Veteran Ave #0",
      "city": "Los Angeles",
      "state": "CA",
      "zip": "90024",
      "neighborhood": "Westwood",
      "lat": 34.0645493,
      "lng": -118.453344,
      "monthly_rent": 4000,
      "bedrooms": 0,
      "bathrooms": 1,
      "sqft": 1000,
      "property_type": "apartment",
      "photos": [
        "https://photos.zillowstatic.com/fp/9844e49e2ff1bf4c9b8fcca58ef872b8-p_e.jpg"
      ],
      "listing_url": "https://www.zillow.com/apartments/los-angeles-ca/bmv-properties/5XjxTv/"
    },
    {
      "external_id": "5XjVDX-2bd",
      "source": "zillow",
      "name": "eight70 - 2 Bed",
      "address_line": "870 Hilgard Ave",
      "city": "Los Angeles",
      "state": "CA",
      "zip": "90024",
      "neighborhood": "Westwood",
      "lat": 34.0648893,
      "lng": -118.4407015,
      "monthly_rent": 4595,
      "bedrooms": 2,
      "bathrooms": 2,
      "sqft": null,
      "property_type": "apartment",
      "photos": [
        "https://photos.zillowstatic.com/fp/782a472d5cbb8414749ed45d8ce560b4-p_e.jpg"
      ],
      "listing_url": "https://www.zillow.com/apartments/los-angeles-ca/eight70/5XjVDX/"
    },
    {
      "external_id": "Cj4bnk-studio",
      "source": "zillow",
      "name": "747 Gayley Ave - Studio",
      "address_line": "747 Gayley Ave",
      "city": "Los Angeles",
      "state": "CA",
      "zip": "90024",
      "neighborhood": "Westwood",
      "lat": 34.0645744,
      "lng": -118.4481798,
      "monthly_rent": 2498,
      "bedrooms": 0,
      "bathrooms": 1,
      "sqft": null,
      "property_type": "apartment",
      "photos": [
        "https://photos.zillowstatic.com/fp/03517ddd1d85b37a286ae28c8c1a179f-p_e.jpg"
      ],
      "listing_url": "https://www.zillow.com/apartments/los-angeles-ca/747-gayley-ave/Cj4bnk/"
    },
    {
      "external_id": "Cj4bnk-1bd",
      "source": "zillow",
      "name": "747 Gayley Ave - 1 Bed",
      "address_line": "747 Gayley Ave",
      "city": "Los Angeles",
      "state": "CA",
      "zip": "90024",
      "neighborhood": "Westwood",
      "lat": 34.0645744,
      "lng": -118.4481798,
      "monthly_rent": 2698,
      "bedrooms": 1,
      "bathrooms": 1,
      "sqft": null,
      "property_type": "apartment",
      "photos": [
        "https://photos.zillowstatic.com/fp/45555190b16da33360829c95e994d0f4-p_e.jpg"
      ],
      "listing_url": "https://www.zillow.com/apartments/los-angeles-ca/747-gayley-ave/Cj4bnk/"
    },
    {
      "external_id": "Cj4bnk-2bd",
      "source": "zillow",
      "name": "747 Gayley Ave - 2 Bed",
      "address_line": "747 Gayley Ave",
      "city": "Los Angeles",
      "state": "CA",
      "zip": "90024",
      "neighborhood": "Westwood",
      "lat": 34.0645744,
      "lng": -118.4481798,
      "monthly_rent": 3898,
      "bedrooms": 2,
      "bathrooms": 2,
      "sqft": null,
      "property_type": "apartment",
      "photos": [
        "https://photos.zillowstatic.com/fp/d156f410ad91e8ed139cf11ced01071e-p_e.jpg"
      ],
      "listing_url": "https://www.zillow.com/apartments/los-angeles-ca/747-gayley-ave/Cj4bnk/"
    },
    {
      "external_id": "5XjHKS-1bd",
      "source": "zillow",
      "name": "Sterling International Towers - 1 Bed",
      "address_line": "10390 Wilshire Blvd",
      "city": "Los Angeles",
      "state": "CA",
      "zip": "90024",
      "neighborhood": "Westwood",
      "lat": 34.0669961,
      "lng": -118.4284319,
      "monthly_rent": 4195,
      "bedrooms": 1,
      "bathrooms": 1,
      "sqft": null,
      "property_type": "apartment",
      "photos": [
        "https://photos.zillowstatic.com/fp/cba56a264730da448b688b9a74bd4447-p_e.jpg"
      ],
      "listing_url": "https://www.zillow.com/apartments/los-angeles-ca/sterling-international-towers/5XjHKS/"
    },
    {
      "external_id": "5XjHKS-2bd",
      "source": "zillow",
      "name": "Sterling International Towers - 2 Bed",
      "address_line": "10390 Wilshire Blvd",
      "city": "Los Angeles",
      "state": "CA",
      "zip": "90024",
      "neighborhood": "Westwood",
      "lat": 34.0669961,
      "lng": -118.4284319,
      "monthly_rent": 5595,
      "bedrooms": 2,
      "bathrooms": 2,
      "sqft": null,
      "property_type": "apartment",
      "photos": [
        "https://photos.zillowstatic.com/fp/ea40a72d6caf93adefee8b81ca430da7-p_e.jpg"
      ],
      "listing_url": "https://www.zillow.com/apartments/los-angeles-ca/sterling-international-towers/5XjHKS/"
    },
    {
      "external_id": "5XjHKS-3bd",
      "source": "zillow",
      "name": "Sterling International Towers - 3 Bed",
      "address_line": "10390 Wilshire Blvd",
      "city": "Los Angeles",
      "state": "CA",
      "zip": "90024",
      "neighborhood": "Westwood",
      "lat": 34.0669961,
      "lng": -118.4284319,
      "monthly_rent": 8995,
      "bedrooms": 3,
      "bathrooms": 3,
      "sqft": null,
      "property_type": "apartment",
      "photos": [
        "https://photos.zillowstatic.com/fp/49e100f33ddc28330a51fae35b80feee-p_e.jpg"
      ],
      "listing_url": "https://www.zillow.com/apartments/los-angeles-ca/sterling-international-towers/5XjHKS/"
    },
    {
      "external_id": "5XpV7H-2bd",
      "source": "zillow",
      "name": "1371 S Beverly Glen Blvd - 2 Bed",
      "address_line": "1371 S Beverly Glen Blvd",
      "city": "Los Angeles",
      "state": "CA",
      "zip": "90024",
      "neighborhood": "Westwood",
      "lat": 34.0627964,
      "lng": -118.426471,
      "monthly_rent": 3198,
      "bedrooms": 2,
      "bathrooms": 2,
      "sqft": null,
      "property_type": "apartment",
      "photos": [
        "https://photos.zillowstatic.com/fp/7ac3ee46fb4352bd82ccc0effbd27a86-p_e.jpg"
      ],
      "listing_url": "https://www.zillow.com/apartments/los-angeles-ca/1371-s.-beverly-glen-blvd./5XpV7H/"
    },
    {
      "external_id": "2127420138",
      "source": "zillow",
      "name": "10647 Wilkins Ave APT 304",
      "address_line": "10647 Wilkins Ave APT 304",
      "city": "Los Angeles",
      "state": "CA",
      "zip": "90024",
      "neighborhood": "Westwood",
      "lat": 34.056903,
      "lng": -118.4331681,
      "monthly_rent": 5750,
      "bedrooms": 2,
      "bathrooms": 4,
      "sqft": 1940,
      "property_type": "townhouse",
      "photos": [],
      "listing_url": "https://www.zillow.com/homedetails/10647-Wilkins-Ave-APT-304-Los-Angeles-CA-90024/2127420138_zpid/"
    },
    {
      "external_id": "wilshire-victoria-1bd",
      "source": "zillow",
      "name": "Wilshire Victoria Westwood - 1 Bed",
      "address_line": "10700 Wilshire Blvd",
      "city": "Los Angeles",
      "state": "CA",
      "zip": "90024",
      "neighborhood": "Westwood",
      "lat": 34.060744,
      "lng": -118.435854,
      "monthly_rent": 5670,
      "bedrooms": 1,
      "bathrooms": 1,
      "sqft": null,
      "property_type": "apartment",
      "photos": [],
      "listing_url": "https://www.zillow.com/los-angeles-ca-90024/apartments/"
    },
    {
      "external_id": "wellworth-108",
      "source": "zillow",
      "name": "Wellworth Apartments APT 108",
      "address_line": "10919 Wellworth Ave APT 108",
      "city": "Los Angeles",
      "state": "CA",
      "zip": "90024",
      "neighborhood": "Westwood",
      "lat": 34.0568938,
      "lng": -118.4434727,
      "monthly_rent": 3100,
      "bedrooms": 1,
      "bathrooms": 1,
      "sqft": null,
      "property_type": "apartment",
      "photos": [],
      "listing_url": "https://www.zillow.com/los-angeles-ca-90024/apartments/"
    },
    {
      "external_id": "westwood-riviera-studio",
      "source": "zillow",
      "name": "Westwood Riviera Apartments - Studio",
      "address_line": "10969 Wellworth Ave",
      "city": "Los Angeles",
      "state": "CA",
      "zip": "90024",
      "neighborhood": "Westwood",
      "lat": 34.0564254,
      "lng": -118.4452349,
      "monthly_rent": 2845,
      "bedrooms": 0,
      "bathrooms": 1,
      "sqft": null,
      "property_type": "apartment",
      "photos": [],
      "listing_url": "https://www.zillow.com/los-angeles-ca-90024/apartments/"
    },
    {
      "external_id": "888-hilgard-217",
      "source": "zillow",
      "name": "888 Hilgard Ave APT 217",
      "address_line": "888 Hilgard Ave APT 217",
      "city": "Los Angeles",
      "state": "CA",
      "zip": "90024",
      "neighborhood": "Westwood",
      "lat": 34.064277,
      "lng": -118.4404836,
      "monthly_rent": 3200,
      "bedrooms": 1,
      "bathrooms": 1,
      "sqft": null,
      "property_type": "apartment",
      "photos": [],
      "listing_url": "https://www.zillow.com/los-angeles-ca-90024/apartments/"
    },
    {
      "external_id": "utama-royale-401",
      "source": "zillow",
      "name": "Utama Royale #401",
      "address_line": "10351 Wilshire Blvd #401",
      "city": "Los Angeles",
      "state": "CA",
      "zip": "90024",
      "neighborhood": "Westwood",
      "lat": 34.0678534,
      "lng": -118.4278685,
      "monthly_rent": 8500,
      "bedrooms": 3,
      "bathrooms": 3.5,
      "sqft": 2765,
      "property_type": "apartment",
      "photos": [],
      "listing_url": "https://www.zillow.com/los-angeles-ca-90024/apartments/"
    },
    {
      "external_id": "kelton-307",
      "source": "zillow",
      "name": "The Kelton Arms #307",
      "address_line": "433 Kelton Ave #307",
      "city": "Los Angeles",
      "state": "CA",
      "zip": "90024",
      "neighborhood": "Westwood",
      "lat": 34.0696439,
      "lng": -118.4539036,
      "monthly_rent": 2950,
      "bedrooms": 1,
      "bathrooms": 1,
      "sqft": null,
      "property_type": "apartment",
      "photos": [],
      "listing_url": "https://www.zillow.com/los-angeles-ca-90024/apartments/"
    },
    {
      "external_id": "969-hilgard-1108",
      "source": "zillow",
      "name": "Park Westwood Towers #1108",
      "address_line": "969 Hilgard Ave Unit 1108",
      "city": "Los Angeles",
      "state": "CA",
      "zip": "90024",
      "neighborhood": "Westwood",
      "lat": 34.0624302,
      "lng": -118.4415784,
      "monthly_rent": 3700,
      "bedrooms": 2,
      "bathrooms": 1.5,
      "sqft": 962,
      "property_type": "condo",
      "photos": [],
      "listing_url": "https://www.zillow.com/homedetails/969-Hilgard-Ave-Los-Angeles-CA-90024/"
    },
    {
      "external_id": "969-hilgard-409",
      "source": "zillow",
      "name": "Park Westwood Towers #409",
      "address_line": "969 Hilgard Ave Unit 409",
      "city": "Los Angeles",
      "state": "CA",
      "zip": "90024",
      "neighborhood": "Westwood",
      "lat": 34.0624302,
      "lng": -118.4415784,
      "monthly_rent": 3200,
      "bedrooms": 1,
      "bathrooms": 1,
      "sqft": 667,
      "property_type": "condo",
      "photos": [],
      "listing_url": "https://www.zillow.com/homedetails/969-Hilgard-Ave-Los-Angeles-CA-90024/"
    },
    {
      "external_id": "the-hilgard-studio",
      "source": "zillow",
      "name": "The Hilgard - Studio",
      "address_line": "972 Hilgard Ave",
      "city": "Los Angeles",
      "state": "CA",
      "zip": "90024",
      "neighborhood": "Westwood",
      "lat": 34.0623109,
      "lng": -118.4413976,
      "monthly_rent": 2725,
      "bedrooms": 0,
      "bathrooms": 1,
      "sqft": null,
      "property_type": "apartment",
      "photos": [],
      "listing_url": "https://www.apartments.com/the-hilgard-los-angeles-ca/f6ncsws/"
    },
    {
      "external_id": "the-hilgard-1bd",
      "source": "zillow",
      "name": "The Hilgard - 1 Bed",
      "address_line": "972 Hilgard Ave",
      "city": "Los Angeles",
      "state": "CA",
      "zip": "90024",
      "neighborhood": "Westwood",
      "lat": 34.0623109,
      "lng": -118.4413976,
      "monthly_rent": 3500,
      "bedrooms": 1,
      "bathrooms": 1,
      "sqft": null,
      "property_type": "apartment",
      "photos": [],
      "listing_url": "https://www.apartments.com/the-hilgard-los-angeles-ca/f6ncsws/"
    },
    {
      "external_id": "the-hilgard-2bd",
      "source": "zillow",
      "name": "The Hilgard - 2 Bed",
      "address_line": "972 Hilgard Ave",
      "city": "Los Angeles",
      "state": "CA",
      "zip": "90024",
      "neighborhood": "Westwood",
      "lat": 34.0623109,
      "lng": -118.4413976,
      "monthly_rent": 4670,
      "bedrooms": 2,
      "bathrooms": 2,
      "sqft": null,
      "property_type": "apartment",
      "photos": [],
      "listing_url": "https://www.apartments.com/the-hilgard-los-angeles-ca/f6ncsws/"
    },
    {
      "external_id": "5j3Pbq-studio",
      "source": "zillow",
      "name": "Century West Apartments - Studio",
      "address_line": "1525 Sawtelle Blvd",
      "city": "Los Angeles",
      "state": "CA",
      "zip": "90025",
      "neighborhood": "Sawtelle",
      "lat": 34.0479599,
      "lng": -118.4498096,
      "monthly_rent": 1695,
      "bedrooms": 0,
      "bathrooms": 1,
      "sqft": null,
      "property_type": "apartment",
      "photos": [],
      "listing_url": "https://www.zillow.com/apartments/los-angeles-ca/century-west-apartments-sawtelle/5j3Pbq/"
    },
    {
      "external_id": "Cqg7Dw-studio",
      "source": "zillow",
      "name": "RBM Westwood - Studio",
      "address_line": "2121 Westwood Blvd",
      "city": "Los Angeles",
      "state": "CA",
      "zip": "90025",
      "neighborhood": "West Los Angeles",
      "lat": 34.0448656,
      "lng": -118.4327057,
      "monthly_rent": 2550,
      "bedrooms": 0,
      "bathrooms": 1,
      "sqft": null,
      "property_type": "apartment",
      "photos": [],
      "listing_url": "https://www.zillow.com/apartments/los-angeles-ca/rbm-westwood-apartments/Cqg7Dw/"
    },
    {
      "external_id": "Cqg7Dw-1bd",
      "source": "zillow",
      "name": "RBM Westwood - 1 Bed",
      "address_line": "2121 Westwood Blvd",
      "city": "Los Angeles",
      "state": "CA",
      "zip": "90025",
      "neighborhood": "West Los Angeles",
      "lat": 34.0448656,
      "lng": -118.4327057,
      "monthly_rent": 2800,
      "bedrooms": 1,
      "bathrooms": 1,
      "sqft": null,
      "property_type": "apartment",
      "photos": [],
      "listing_url": "https://www.zillow.com/apartments/los-angeles-ca/rbm-westwood-apartments/Cqg7Dw/"
    },
    {
      "external_id": "Cqg7Dw-2bd",
      "source": "zillow",
      "name": "RBM Westwood - 2 Bed",
      "address_line": "2121 Westwood Blvd",
      "city": "Los Angeles",
      "state": "CA",
      "zip": "90025",
      "neighborhood": "West Los Angeles",
      "lat": 34.0448656,
      "lng": -118.4327057,
      "monthly_rent": 5350,
      "bedrooms": 2,
      "bathrooms": 2,
      "sqft": null,
      "property_type": "apartment",
      "photos": [],
      "listing_url": "https://www.zillow.com/apartments/los-angeles-ca/rbm-westwood-apartments/Cqg7Dw/"
    },
    {
      "external_id": "945-gayley-1bd",
      "source": "zillow",
      "name": "945 Gayley Ave - 1 Bed",
      "address_line": "945 Gayley Ave",
      "city": "Los Angeles",
      "state": "CA",
      "zip": "90024",
      "neighborhood": "Westwood",
      "lat": 34.0630685,
      "lng": -118.4482115,
      "monthly_rent": 2800,
      "bedrooms": 1,
      "bathrooms": 1,
      "sqft": null,
      "property_type": "apartment",
      "photos": [],
      "listing_url": "https://www.apartments.com/945-gayley-inc-los-angeles-ca/fvld7mr/"
    },
    {
      "external_id": "1260-veteran-317",
      "source": "zillow",
      "name": "1260 Veteran Ave #317",
      "address_line": "1260 Veteran Ave #317",
      "city": "Los Angeles",
      "state": "CA",
      "zip": "90024",
      "neighborhood": "Westwood",
      "lat": 34.0566577,
      "lng": -118.4466771,
      "monthly_rent": 2650,
      "bedrooms": 1,
      "bathrooms": 1,
      "sqft": null,
      "property_type": "apartment",
      "photos": [
        "https://photos.zillowstatic.com/fp/175ab9a7af04efe63740ee399ce666dc-p_e.jpg"
      ],
      "listing_url": "https://www.zillow.com/los-angeles-ca-90024/apartments/"
    },
    {
      "external_id": "1441-veteran-107",
      "source": "zillow",
      "name": "1441 Veteran Ave #107",
      "address_line": "1441 Veteran Ave #107",
      "city": "Los Angeles",
      "state": "CA",
      "zip": "90024",
      "neighborhood": "Westwood",
      "lat": 34.0527489,
      "lng": -118.4438632,
      "monthly_rent": 2400,
      "bedrooms": 1,
      "bathrooms": 1,
      "sqft": null,
      "property_type": "apartment",
      "photos": [
        "https://photos.zillowstatic.com/fp/c999ed52c52a92eb20a0e120c7aaaa85-p_e.jpg"
      ],
      "listing_url": "https://www.zillow.com/los-angeles-ca-90024/apartments/"
    },
    {
      "external_id": "10558-eastborne",
      "source": "zillow",
      "name": "10558 Eastborne Ave",
      "address_line": "10558 Eastborne Ave",
      "city": "Los Angeles",
      "state": "CA",
      "zip": "90024",
      "neighborhood": "Westwood",
      "lat": 34.0549017,
      "lng": -118.4292492,
      "monthly_rent": 2775,
      "bedrooms": 1,
      "bathrooms": 1,
      "sqft": null,
      "property_type": "apartment",
      "photos": [],
      "listing_url": "https://www.apartments.com/10558-eastborne-ave-los-angeles-ca/bm0xwn9/"
    },
    {
      "external_id": "10982-roebling",
      "source": "zillow",
      "name": "10982 Roebling Ave",
      "address_line": "10982 Roebling Ave Unit 428",
      "city": "Los Angeles",
      "state": "CA",
      "zip": "90024",
      "neighborhood": "Westwood",
      "lat": 34.0645971,
      "lng": -118.4492095,
      "monthly_rent": 2775,
      "bedrooms": 1,
      "bathrooms": 1,
      "sqft": null,
      "property_type": "apartment",
      "photos": [],
      "listing_url": "https://www.apartments.com/10982-roebling-ave-los-angeles-ca/twsbb7b/"
    },
    {
      "external_id": "10798-lindbrook",
      "source": "zillow",
      "name": "10798 Lindbrook Dr",
      "address_line": "10798 Lindbrook Dr",
      "city": "Los Angeles",
      "state": "CA",
      "zip": "90024",
      "neighborhood": "Westwood",
      "lat": 34.060854,
      "lng": -118.439944,
      "monthly_rent": 3200,
      "bedrooms": 2,
      "bathrooms": 1,
      "sqft": null,
      "property_type": "apartment",
      "photos": [],
      "listing_url": "https://www.apartments.com/10798-lindbrook-dr-los-angeles-ca/hw7tmf0/"
    },
    {
      "external_id": "400-landfair-4",
      "source": "zillow",
      "name": "400 Landfair Ave Unit 4",
      "address_line": "400 Landfair Ave Unit 4",
      "city": "Los Angeles",
      "state": "CA",
      "zip": "90024",
      "neighborhood": "Westwood",
      "lat": 34.070465,
      "lng": -118.453068,
      "monthly_rent": 3100,
      "bedrooms": 2,
      "bathrooms": 1,
      "sqft": null,
      "property_type": "apartment",
      "photos": [],
      "listing_url": "https://www.zillow.com/los-angeles-ca-90024/apartments/"
    },
    {
      "external_id": "1942-westwood-1bd",
      "source": "zillow",
      "name": "1942 Westwood Blvd - 1 Bed",
      "address_line": "1942 Westwood Blvd",
      "city": "Los Angeles",
      "state": "CA",
      "zip": "90025",
      "neighborhood": "West Los Angeles",
      "lat": 34.0475789,
      "lng": -118.4346931,
      "monthly_rent": 2950,
      "bedrooms": 1,
      "bathrooms": 1,
      "sqft": null,
      "property_type": "apartment",
      "photos": [],
      "listing_url": "https://www.apartments.com/1942-westwood-blvd-los-angeles-ca/cqthzld/"
    }
  ]
}
